LICENSE
README.rst
setup.py
wlkata_mirobot/__init__.py
wlkata_mirobot/wlkata_mirobot.py
wlkata_mirobot/wlkata_mirobot_exceptions.py
wlkata_mirobot/wlkata_mirobot_serial.py
wlkata_mirobot/wlkata_mirobot_status.py
wlkata_mirobot/resources/__init__.py
wlkata_mirobot/resources/reset.xml
wlkata_mirobot_python.egg-info/PKG-INFO
wlkata_mirobot_python.egg-info/SOURCES.txt
wlkata_mirobot_python.egg-info/dependency_links.txt
wlkata_mirobot_python.egg-info/requires.txt
wlkata_mirobot_python.egg-info/top_level.txt