Metadata-Version: 2.1
Name: wlkata-mirobot-python
Version: 0.1.10
Summary: WKlata Mirobot Python SDK
Home-page: https://github.com/mushroom-x/wlkata-mirobot-python
Author: Shunkai Xing
Author-email: xingshunkai@qq.com
License: UNKNOWN
Platform: UNKNOWN
Classifier: 
Classifier:                  Development Status :: 4 - Beta
Classifier:                  Programming Language :: Python :: 3 :: Only
Classifier:                  Programming Language :: Python :: 3.6
Classifier:                  Programming Language :: Python :: 3.7
Classifier:                  Programming Language :: Python :: 3.8
Classifier:                  Programming Language :: Python :: 3.9
Classifier:                  License :: OSI Approved :: MIT License
Classifier:                  Operating System :: OS Independent
Classifier:                  Operating System :: Microsoft :: Windows
Classifier:                  Operating System :: POSIX
Classifier:                  Operating System :: Unix
Classifier:                  Operating System :: MacOS
Classifier:                  Topic :: Scientific/Engineering
Classifier:                  Topic :: Education
Classifier:                  Topic :: Documentation
Classifier:                  Topic :: Home Automation
Classifier:                  Topic :: Scientific/Engineering :: Artificial Intelligence
Classifier:                  Topic :: Scientific/Engineering :: Electronic Design Automation (EDA)
Classifier:                  Topic :: Scientific/Engineering :: Image Recognition
Classifier:                  Topic :: Software Development :: Embedded Systems
Classifier:                  Topic :: Software Development :: Version Control :: Git
Classifier:                  Topic :: Terminals :: Serial
Classifier:                  Intended Audience :: Education
Classifier:                  Intended Audience :: Science/Research
Classifier:                  Intended Audience :: Manufacturing
Classifier:                  Intended Audience :: Developers
Classifier:                  
Requires-Python: >=3.6
License-File: LICENSE
